baleh/__init__.py
baleh/client.py
baleh/objects/__init__.py
baleh/objects/chat.py
baleh/objects/message.py
baleh/objects/user.py
baleh/utils/__init__.py
baleh/utils/helpers.py
baleh-0.2.3.dist-info/licenses/LICENSE
baleh-0.2.3.dist-info/METADATA
baleh-0.2.3.dist-info/WHEEL
baleh-0.2.3.dist-info/top_level.txt
baleh-0.2.3.dist-info/RECORD
