Metadata-Version: 2.4
Name: baleh
Version: 0.2.3
Summary: A powerful Python library for developing Bale messenger bots
Home-page: https://github.com/hamidrashidi98/baleh
Author: Hamid Rashidi
Author-email: spiderhamidman@gmail.com
License: MIT
Classifier: Programming Language :: Python :: 3
Classifier: License :: OSI Approved :: MIT License
Classifier: Operating System :: OS Independent
Classifier: Intended Audience :: Developers
Classifier: Topic :: Communications :: Chat
Requires-Python: >=3.7
License-File: LICENSE
Requires-Dist: aiohttp>=3.8.0
Requires-Dist: Pillow>=9.0.0
Dynamic: author
Dynamic: author-email
Dynamic: classifier
Dynamic: description
Dynamic: description-content-type
Dynamic: home-page
Dynamic: license
Dynamic: license-file
Dynamic: requires-dist
Dynamic: requires-python
Dynamic: summary
